vxyowsup/__init__.py
vxyowsup/whatsapp.py
vxyowsup/tests/__init__.py
vxyowsup/tests/test_whatsapp.py
vxyowsup-0.1.8.dist-info/DESCRIPTION.rst
vxyowsup-0.1.8.dist-info/METADATA
vxyowsup-0.1.8.dist-info/RECORD
vxyowsup-0.1.8.dist-info/WHEEL
vxyowsup-0.1.8.dist-info/metadata.json
vxyowsup-0.1.8.dist-info/top_level.txt
